statcan_dialogue_dataset/__init__.py
statcan_dialogue_dataset/metadata.py
statcan_dialogue_dataset/utils.py
statcan_dialogue_dataset/version.py
statcan_dialogue_dataset/_data/__init__.py
statcan_dialogue_dataset/_data/basic_info.json
statcan_dialogue_dataset/_data/basic_info.py
statcan_dialogue_dataset/_data/code_sets_map.json
statcan_dialogue_dataset/_data/code_sets_map.py
statcan_dialogue_dataset/_data/footnotes.json
statcan_dialogue_dataset/_data/footnotes.py
statcan_dialogue_dataset/_data/members.py
statcan_dialogue_dataset/_data/members.zip
statcan_dialogue_dataset/_data/metadata_hierarchy.json
statcan_dialogue_dataset/_data/metadata_hierarchy.py
statcan_dialogue_dataset/_data/title_to_pid.json
statcan_dialogue_dataset/_data/title_to_pid.py
statcan_dialogue_dataset/cli/__init__.py
statcan_dialogue_dataset/cli/update_version.py
statcan_dialogue_dataset/cli/process/__init__.py
statcan_dialogue_dataset/cli/process/code_sets.py
statcan_dialogue_dataset/cli/process/full_metadata.py
statcan_dialogue_dataset/cli/process/metadata_hierarchy.py
statcan_dialogue_dataset-0.2.0.dist-info/METADATA
statcan_dialogue_dataset-0.2.0.dist-info/WHEEL
statcan_dialogue_dataset-0.2.0.dist-info/top_level.txt
statcan_dialogue_dataset-0.2.0.dist-info/RECORD
