Metadata-Version: 2.1
Name: statcan-dialogue-dataset
Version: 0.2.0
Summary: The Statcan Dialogue Dataset
Home-page: https://github.com/McGill-NLP/statcan-dialogue-dataset
Author: Xing Han Lu, Siva Reddy, Harm de Vries
Author-email: statcan.dialogue.dataset@mila.quebec
License: UNKNOWN
Platform: UNKNOWN
Classifier: Programming Language :: Python :: 3
Classifier: License :: OSI Approved :: MIT License
Classifier: Operating System :: OS Independent
Requires-Python: >=3.7
Requires-Dist: pandas
Provides-Extra: dev
Requires-Dist: black ; extra == 'dev'
Requires-Dist: wheel ; extra == 'dev'
